setup.py
distributions_llg/Binomialdistribution.py
distributions_llg/Gaussiandistribution.py
distributions_llg/Generaldistribution.py
distributions_llg/__init__.py
distributions_llg.egg-info/PKG-INFO
distributions_llg.egg-info/SOURCES.txt
distributions_llg.egg-info/dependency_links.txt
distributions_llg.egg-info/not-zip-safe
distributions_llg.egg-info/top_level.txt