Metadata-Version: 1.0
Name: distributions-llg
Version: 0.3
Summary: Gaussian and Binomial distributions
Home-page: UNKNOWN
Author: Udacity---modified by myself as part of the exercise
Author-email: UNKNOWN
License: UNKNOWN
Platform: UNKNOWN
